kmspy/__init__.py
kmspy/_asyncio/__init__.py
kmspy/_asyncio/_event_loop.py
kmspy/_asyncio/_tasque.py
kmspy/data/__init__.py
kmspy/data/dataset.py
kmspy/data/prefetch_generator.py
kmspy/multiprocessing/__init__.py
kmspy/multiprocessing/process.py
kmspy/utils/__init__.py
kmspy/utils/_proxy_class.py
kmspy/utils/_utils.py
tests/__init__.py
tests/test.py
kmspy-0.0.27.dist-info/METADATA
kmspy-0.0.27.dist-info/WHEEL
kmspy-0.0.27.dist-info/top_level.txt
kmspy-0.0.27.dist-info/RECORD
