Metadata-Version: 2.1
Name: kmspy
Version: 0.0.27
Home-page: 
Author: KMS
Author-email: su4651@gmail.com
Classifier: Programming Language :: Python :: 3
Classifier: License :: OSI Approved :: MIT License
Classifier: Operating System :: OS Independent
Requires-Python: >=3.6
Requires-Dist: numpy
